appwindows/__init__.py
appwindows/__init__.pyi
appwindows/appwindows.cpython-314-x86_64-linux-gnu.so
appwindows/py.typed
appwindows/exceptions/__init__.py
appwindows/exceptions/__init__.pyi
appwindows/geometry/__init__.py
appwindows/geometry/__init__.pyi
appwindows-1.2.2.dist-info/METADATA
appwindows-1.2.2.dist-info/WHEEL
appwindows-1.2.2.dist-info/RECORD
