Metadata-Version: 2.1
Name: appwindows
Version: 1.2.2
Summary: The appwindows library solves the problem of working with a graphical shell on different operating systems.
Author-Email: "Terochkin A.S" <apparser.development@gmail.com>
Classifier: Programming Language :: Python :: 3
Classifier: License :: OSI Approved :: BSD License
Classifier: Operating System :: Microsoft :: Windows :: Windows 10
Classifier: Operating System :: Microsoft :: Windows :: Windows 11
Classifier: Operating System :: POSIX :: Linux
Classifier: Environment :: X11 Applications
Classifier: Environment :: Win32 (MS Windows)
Classifier: Typing :: Stubs Only
Project-URL: Repository, https://github.com/lexter0705/appwindows
Project-URL: Issues, https://github.com/lexter0705/appwindows/issues
Project-URL: Docs, https://apparser.gitbook.io/appwindows
Requires-Python: >=3.8
Requires-Dist: numpy>=2.0
